cli/__init.py__
cli/fsqbench.py
cli/fsqc.py
fsq/__init__.py
fsq/api.py
fsq/contextmanager.py
fsq/misc.py
fsq/strenum_compat.py
fsq/struct.py
pyfsq-0.1.7.dist-info/METADATA
pyfsq-0.1.7.dist-info/WHEEL
pyfsq-0.1.7.dist-info/entry_points.txt
pyfsq-0.1.7.dist-info/licenses/LICENSE
pyfsq-0.1.7.dist-info/RECORD
