Metadata-Version: 2.4
Name: pyfsq
Version: 0.1.7
Summary: Python-based console client and API for transferring data to FSQ server
Project-URL: Homepage, https://github.com/GSI-HPC/pyfsq
Project-URL: Issues, https://github.com/GSI-HPC/pyfsq/issues
Author-email: Thomas Stibor <t.stibor@gsi.de>
License-File: LICENSE
Classifier: License :: OSI Approved :: GNU General Public License v3 or later (GPLv3+)
Classifier: Operating System :: OS Independent
Classifier: Programming Language :: Python :: 3
Requires-Python: >=3.7
